nekodict/__main__.py
nekodict-0.1.4.dist-info/LICENSE
nekodict-0.1.4.dist-info/METADATA
nekodict-0.1.4.dist-info/WHEEL
nekodict-0.1.4.dist-info/entry_points.txt
nekodict-0.1.4.dist-info/top_level.txt
nekodict-0.1.4.dist-info/RECORD
