Metadata-Version: 2.1
Name: nekodict
Version: 0.1.4
Summary: Neko Dictionary is a light-weight command line EN-ZH dictionary.
Author-email: BeautyyuYanli <beautyyuyanli@gmail.com>
License: GNU GENERAL PUBLIC LICENSE
Project-URL: Source, https://github.com/BeautyYuYanli/nekodict
Keywords: dictionary,terminal
Requires-Python: >=3.3
License-File: LICENSE
Requires-Dist: beautifulsoup4 (>=4.9)
Requires-Dist: requests (>=2.25)
Requires-Dist: termcolor (>=2.0.1)
Requires-Dist: playsound (>=1.3)
